LICENSE
MANIFEST.in
README.rst
setup.py
requirements/dist.txt
requirements/test.txt
verboselib/__init__.py
verboselib/_utils.py
verboselib/core.py
verboselib/helpers.py
verboselib/translations.py
verboselib/version.py
verboselib.egg-info/PKG-INFO
verboselib.egg-info/SOURCES.txt
verboselib.egg-info/dependency_links.txt
verboselib.egg-info/entry_points.txt
verboselib.egg-info/requires.txt
verboselib.egg-info/top_level.txt
verboselib.egg-info/zip-safe
verboselib/cli/__init__.py
verboselib/cli/command_base.py
verboselib/cli/command_compile.py
verboselib/cli/command_extract.py
verboselib/cli/defaults.py
verboselib/cli/encoding.py
verboselib/cli/gettext_tools.py
verboselib/cli/lang.py
verboselib/cli/main.py
verboselib/cli/paths.py
verboselib/cli/text.py
verboselib/cli/utils.py