Metadata-Version: 2.1
Name: verboselib
Version: 1.1.0
Summary: A little I18N framework for libraries and applications
Home-page: https://github.com/oblalex/verboselib/tree/v1.1.0
Author: Oleksandr Oblovatnyi
Author-email: oblovatniy@gmail.com
License: MIT
Keywords: library,l18n,localization,lazy,string,framework,gettext
Platform: UNKNOWN
Classifier: Development Status :: 5 - Production/Stable
Classifier: Intended Audience :: Developers
Classifier: License :: OSI Approved :: MIT License
Classifier: Natural Language :: English
Classifier: Operating System :: MacOS :: MacOS X
Classifier: Operating System :: Microsoft :: Windows
Classifier: Operating System :: POSIX
Classifier: Programming Language :: Python :: 3
Classifier: Topic :: Software Development :: Libraries
Requires-Python: >=3.7
